README.md
setup.py
attrify/__init__.py
attrify/attrified_dict.py
attrify.egg-info/PKG-INFO
attrify.egg-info/SOURCES.txt
attrify.egg-info/dependency_links.txt
attrify.egg-info/top_level.txt